odoo/addons/l10n_br_coa_simple/README.rst
odoo/addons/l10n_br_coa_simple/__init__.py
odoo/addons/l10n_br_coa_simple/__manifest__.py
odoo/addons/l10n_br_coa_simple/hooks.py
odoo/addons/l10n_br_coa_simple/data/account.account.template.csv
odoo/addons/l10n_br_coa_simple/data/account_group.xml
odoo/addons/l10n_br_coa_simple/data/l10n_br_coa.account.tax.group.account.template.csv
odoo/addons/l10n_br_coa_simple/data/l10n_br_coa_simple_template.xml
odoo/addons/l10n_br_coa_simple/data/l10n_br_coa_simple_template_post.xml
odoo/addons/l10n_br_coa_simple/demo/account_journal.xml
odoo/addons/l10n_br_coa_simple/i18n/l10n_br_coa_simple.pot
odoo/addons/l10n_br_coa_simple/i18n/pt_BR.po
odoo/addons/l10n_br_coa_simple/readme/CONFIGURE.rst
odoo/addons/l10n_br_coa_simple/readme/CONTRIBUTORS.rst
odoo/addons/l10n_br_coa_simple/readme/DESCRIPTION.rst
odoo/addons/l10n_br_coa_simple/readme/INSTALL.rst
odoo/addons/l10n_br_coa_simple/readme/ROADMAP.rst
odoo/addons/l10n_br_coa_simple/readme/USAGE.rst
odoo/addons/l10n_br_coa_simple/static/description/icon.png
odoo/addons/l10n_br_coa_simple/static/description/index.html
odoo/addons/l10n_br_coa_simple/tests/__init__.py
odoo/addons/l10n_br_coa_simple/tests/test_l10n_br_coa_simple.py
odoo14_addon_l10n_br_coa_simple-14.0.3.2.0.dist-info/METADATA
odoo14_addon_l10n_br_coa_simple-14.0.3.2.0.dist-info/WHEEL
odoo14_addon_l10n_br_coa_simple-14.0.3.2.0.dist-info/top_level.txt
odoo14_addon_l10n_br_coa_simple-14.0.3.2.0.dist-info/RECORD
