Metadata-Version: 2.1
Name: odoo14-addon-l10n_br_coa_simple
Version: 14.0.3.2.0
Summary: Plano de Contas ITG 1000 para Microempresas e Empresa de Pequeno Porte
Home-page: https://github.com/OCA/l10n-brazil
Author: Akretion, Odoo Community Association (OCA)
Author-email: support@odoo-community.org
License: AGPL-3
Classifier: Programming Language :: Python
Classifier: Framework :: Odoo
Classifier: Framework :: Odoo :: 14.0
Classifier: License :: OSI Approved :: GNU Affero General Public License v3
Classifier: Development Status :: 5 - Production/Stable
Requires-Python: >=3.6
Requires-Dist: odoo14-addon-l10n-br-coa
Requires-Dist: odoo<14.1dev,>=14.0a
